{"nodes": {"DDoS": {"pos": [449, 46], "properties": {}}, "Malware Attacks": {"pos": [281, 110], "properties": {}}, "Network Scanning": {"pos": [187, 195], "properties": {}}, "Password Cracking": {"pos": [197, 310], "properties": {}}, "Social Engineering": {"pos": [125, 484], "properties": {}}, "Capital of ZERO": {"pos": [500, 200], "properties": {"capital": true}}}, "edges": [{"source": "Social Engineering", "target": "Password Cracking"}, {"source": "Password Cracking", "target": "Network Scanning"}, {"source": "Network Scanning", "target": "Malware Attacks"}, {"source": "Malware Attacks", "target": "DDoS"}, {"source": "DDoS", "target": "Capital of ZERO"}, {"source": "Social Engineering", "target": "Capital of ZERO"}]}